twinsqla/__init__.py
twinsqla/_dynamic_parser.py
twinsqla/_querybindbuilder.py
twinsqla/_resultbuilder.py
twinsqla/_sqlbuilder.py
twinsqla/_support.py
twinsqla/codegenerator.py
twinsqla/exceptions.py
twinsqla/python_grammer.lark
twinsqla/sql.two_way.lark
twinsqla/twinsqla.py
twinsqla-0.0.4.dist-info/entry_points.txt
twinsqla-0.0.4.dist-info/LICENSE
twinsqla-0.0.4.dist-info/WHEEL
twinsqla-0.0.4.dist-info/METADATA
twinsqla-0.0.4.dist-info/RECORD
