Metadata-Version: 2.1
Name: twinsqla
Version: 0.0.4
Summary: TWinSQLA is a light framework for mapping SQL statements to python functions and methods.
Home-page: https://github.com/kajitiluna/twinsqla
License: Apache-2.0
Author: Yoshiki Kajihara
Requires-Python: >=3.6,<4.0
Classifier: License :: OSI Approved :: Apache Software License
Classifier: Programming Language :: Python :: 3
Classifier: Programming Language :: Python :: 3.6
Classifier: Programming Language :: Python :: 3.7
Classifier: Programming Language :: Python :: 3.8
Classifier: Programming Language :: Python :: 3.9
Requires-Dist: lark-parser (>=0.11.1,<0.12.0)
Requires-Dist: sqlalchemy (>=1.3,<2.0)
Project-URL: Repository, https://github.com/kajitiluna/twinsqla
